pGadgetron/__init__.py
pSTIR/__init__.py
pUtilities/__init__.py
sirf/__init__.py
sirf/pGadgetron.py
sirf/pSTIR.py
sirf/pUtilities.py
sirf/pygadgetron.py
sirf/pyiutilities.py
sirf/pystir.py
sirf-1.0.0.dist-info/METADATA
sirf-1.0.0.dist-info/RECORD
sirf-1.0.0.dist-info/WHEEL
sirf-1.0.0.dist-info/top_level.txt
