Metadata-Version: 2.1
Name: sirf
Version: 1.0.0
Summary: CCP PET-MR SIRF
Home-page: https://github.com/CCPPETMR/SIRF
Author: CCP PET-MR
Author-email: ccppetmr@stfc.ac.uk
License: Apache 2.0
Keywords: image reconstruction pet mr medical imaging
Platform: any
Classifier: Development Status :: 5 - Production/Stable
Classifier: Programming Language :: Python :: 2
Classifier: Programming Language :: Python :: 2.6
Classifier: Programming Language :: Python :: 2.7
Classifier: Programming Language :: Python :: 3
Classifier: Programming Language :: Python :: 3.2
Classifier: Programming Language :: Python :: 3.3
Classifier: Programming Language :: Python :: 3.4
Classifier: Programming Language :: Python :: 3.5
Classifier: Programming Language :: Python :: 3.6
Classifier: Programming Language :: Python :: 3.7
